{
  "_id": "QtmVEreNIWEVOoLR",
  "name": "Ring of Protection",
  "type": "equipment",
  "img": "icons/equipment/finger/ring-cabochon-silver-gold-red.webp",
  "system": {
    "description": {
      "value": "<p><em>(Requires attunement)</em></p>\n<p>You gain a +1 bonus to AC and saving throws while wearing this ring.</p>",
      "chat": "",
      "unidentified": ""
    },
    "source": {
      "custom": "",
      "book": "SRD 5.1",
      "page": "",
      "license": "CC-BY-4.0"
    },
    "quantity": 1,
    "weight": 0,
    "price": {
      "value": 3500,
      "denomination": "gp"
    },
    "attunement": 1,
    "equipped": false,
    "rarity": "rare",
    "identified": true,
    "activation": {
      "type": "",
      "cost": null,
      "condition": ""
    },
    "duration": {
      "value": "",
      "units": ""
    },
    "cover": null,
    "crewed": false,
    "target": {
      "value": null,
      "width": null,
      "units": "",
      "type": "self"
    },
    "range": {
      "value": null,
      "long": null,
      "units": "self"
    },
    "uses": {
      "value": null,
      "max": "",
      "per": null,
      "recovery": ""
    },
    "consume": {
      "type": "",
      "target": null,
      "amount": null
    },
    "ability": "",
    "actionType": "",
    "attackBonus": "",
    "chatFlavor": "",
    "critical": {
      "threshold": null,
      "damage": ""
    },
    "damage": {
      "parts": [],
      "versatile": ""
    },
    "formula": "",
    "save": {
      "ability": "",
      "dc": null,
      "scaling": "spell"
    },
    "armor": {
      "value": 0,
      "type": "trinket",
      "dex": 0
    },
    "hp": {
      "value": 0,
      "max": 0,
      "dt": null,
      "conditions": ""
    },
    "baseItem": "",
    "speed": {
      "value": null,
      "conditions": ""
    },
    "strength": null,
    "stealth": false,
    "proficient": null
  },
  "effects": [
    {
      "_id": "q1wbe9ru251bfnhg",
      "changes": [
        {
          "key": "system.attributes.ac.bonus",
          "mode": 2,
          "value": "+1",
          "priority": null
        },
        {
          "key": "system.bonuses.abilities.save",
          "mode": 2,
          "value": "+1",
          "priority": null
        }
      ],
      "disabled": false,
      "duration": {
        "startTime": null,
        "seconds": null,
        "combat": null,
        "rounds": null,
        "turns": null,
        "startRound": null,
        "startTurn": null
      },
      "icon": "icons/equipment/finger/ring-cabochon-silver-gold-red.webp",
      "label": "Ring of Protection",
      "origin": "Compendium.dnd5e.items.QtmVEreNIWEVOoLR",
      "transfer": true,
      "flags": {},
      "tint": null,
      "sort": 0,
      "_key": "!items.effects!QtmVEreNIWEVOoLR.q1wbe9ru251bfnhg"
    }
  ],
  "folder": "aJgMxnZED9XdoN2W",
  "sort": 0,
  "ownership": {
    "default": 0
  },
  "flags": {},
  "_stats": {
    "systemId": "dnd5e",
    "systemVersion": "3.0.0",
    "coreVersion": "11.315",
    "createdTime": 1661787233653,
    "modifiedTime": 1701903922195,
    "lastModifiedBy": "dnd5ebuilder0000"
  },
  "_key": "!items!QtmVEreNIWEVOoLR"
}
