{
  "_id": "NgwrqNa6kkgoPW2Q",
  "name": "Shield +1",
  "type": "equipment",
  "img": "icons/equipment/shield/round-wooden-boss-gold-brown.webp",
  "system": {
    "description": {
      "value": "<p>While holding this shield, you have a bonus to AC of +1. This bonus is in addition to the shield's normal bonus to AC.</p>",
      "chat": "",
      "unidentified": ""
    },
    "source": {
      "custom": "",
      "book": "SRD 5.1",
      "page": "",
      "license": "CC-BY-4.0"
    },
    "quantity": 1,
    "weight": 6,
    "price": {
      "value": 1500,
      "denomination": "gp"
    },
    "attunement": 0,
    "equipped": false,
    "rarity": "uncommon",
    "identified": true,
    "activation": {
      "type": "",
      "cost": null,
      "condition": ""
    },
    "duration": {
      "value": "",
      "units": ""
    },
    "cover": null,
    "crewed": false,
    "target": {
      "value": null,
      "width": null,
      "units": "",
      "type": "self"
    },
    "range": {
      "value": null,
      "long": null,
      "units": "self"
    },
    "uses": {
      "value": null,
      "max": "",
      "per": null,
      "recovery": ""
    },
    "consume": {
      "type": "",
      "target": null,
      "amount": null
    },
    "ability": null,
    "actionType": "",
    "attackBonus": "",
    "chatFlavor": "",
    "critical": {
      "threshold": null,
      "damage": ""
    },
    "damage": {
      "parts": [],
      "versatile": ""
    },
    "formula": "",
    "save": {
      "ability": "",
      "dc": null,
      "scaling": "spell"
    },
    "armor": {
      "value": 3,
      "type": "shield",
      "dex": null
    },
    "hp": {
      "value": 0,
      "max": 0,
      "dt": null,
      "conditions": ""
    },
    "baseItem": "",
    "speed": {
      "value": null,
      "conditions": ""
    },
    "strength": null,
    "stealth": false,
    "proficient": null
  },
  "effects": [],
  "folder": null,
  "sort": 0,
  "ownership": {
    "default": 0
  },
  "flags": {},
  "_stats": {
    "systemId": "dnd5e",
    "systemVersion": "2.2.2",
    "coreVersion": "10.291",
    "createdTime": 1661787233633,
    "modifiedTime": 1690539669653,
    "lastModifiedBy": "dnd5ebuilder0000"
  },
  "_key": "!items!NgwrqNa6kkgoPW2Q"
}
