{
  "_id": "OSFOLPMCKC2WCO44",
  "name": "Synaptic Static",
  "ownership": {
    "default": 0
  },
  "type": "spell",
  "system": {
    "description": {
      "value": "<p>You choose a point within range and cause psychic energy to explode there. Each creature in a 20-foot-radius sphere centered on that point must make an <strong>Intelligence saving throw</strong>. A creature with an Intelligence score of 2 or lower can't be affected by this spell. A target takes <strong>8d6 psychic damage</strong> on a failed save, or half as much damage on a successful one.</p><p>After a failed save, a target has muddled thoughts for 1 minute. During that time, it rolls a d6 and subtracts the number rolled from all its attack rolls and ability checks, as well as its <strong>Constitution saving throw</strong>s to maintain concentration. The target can make an <strong>Intelligence saving throw</strong> at the end of each of its turns, ending the effect on itself on a success.</p>",
      "chat": "",
      "unidentified": ""
    },
    "source": "SRD 5.1",
    "activation": {
      "type": "action",
      "cost": 1,
      "condition": ""
    },
    "duration": {
      "value": "",
      "units": "inst"
    },
    "cover": null,
    "target": {
      "value": 20,
      "width": null,
      "units": "ft",
      "type": "sphere"
    },
    "range": {
      "value": 120,
      "long": null,
      "units": "ft"
    },
    "uses": {
      "value": null,
      "max": "",
      "per": null,
      "recovery": ""
    },
    "consume": {
      "type": "",
      "target": null,
      "amount": null
    },
    "ability": "",
    "actionType": "save",
    "attackBonus": "",
    "chatFlavor": "",
    "critical": {
      "threshold": null,
      "damage": ""
    },
    "damage": {
      "parts": [
        [
          "8d6",
          "psychic"
        ]
      ],
      "versatile": ""
    },
    "formula": "",
    "save": {
      "ability": "int",
      "dc": null,
      "scaling": "spell"
    },
    "level": 5,
    "school": "enc",
    "components": {
      "vocal": true,
      "somatic": true,
      "material": false,
      "ritual": false,
      "concentration": false
    },
    "materials": {
      "value": "",
      "consumed": false,
      "cost": 0,
      "supply": 0
    },
    "preparation": {
      "mode": "prepared",
      "prepared": false
    },
    "scaling": {
      "mode": "none",
      "formula": ""
    }
  },
  "sort": 0,
  "flags": {},
  "img": "icons/magic/air/fog-gas-smoke-swirling-pink.webp",
  "effects": [],
  "folder": null,
  "_stats": {
    "systemId": "dnd5e",
    "systemVersion": "2.1.0",
    "coreVersion": "10.291",
    "createdTime": 1675986798490,
    "modifiedTime": 1675989935032,
    "lastModifiedBy": "RightHandOfVecna"
  }
}
