{
  "_id": "fiDDtaR8tNzDtvds",
  "name": "Feat: Mounted Combatant",
  "ownership": {
    "default": 0
  },
  "type": "feat",
  "system": {
    "description": {
      "value": "<p>You are a dangerous foe to face while mounted. While you are mounted and aren't incapacitated, you gain the following benefits:</p>\n<ul>\n<li>You have advantage on melee attack rolls against any unmounted creature that is smaller than your mount.</li>\n<li>You can force an attack targeted at your mount to target you instead.</li>\n<li>If your mount would take damage, you can choose to take the damage instead.</li>\n<li>If your mount is subjected to an effect that allows it to make a Dexterity saving throw to take only half damage, it instead takes no damage if it succeeds on the saving throw, and only half damage if it fails.</li>\n</ul>",
      "chat": "",
      "unidentified": ""
    },
    "source": "SRD 5.1",
    "activation": {
      "type": "",
      "cost": null,
      "condition": ""
    },
    "duration": {
      "value": "",
      "units": ""
    },
    "cover": null,
    "target": {
      "value": null,
      "width": null,
      "units": "",
      "type": ""
    },
    "range": {
      "value": null,
      "long": null,
      "units": ""
    },
    "uses": {
      "value": null,
      "max": "",
      "per": null,
      "recovery": ""
    },
    "consume": {
      "type": "",
      "target": null,
      "amount": null
    },
    "ability": null,
    "actionType": "",
    "attackBonus": "",
    "chatFlavor": "",
    "critical": {
      "threshold": null,
      "damage": ""
    },
    "damage": {
      "parts": [],
      "versatile": ""
    },
    "formula": "",
    "save": {
      "ability": "",
      "dc": null,
      "scaling": "spell"
    },
    "type": {
      "value": "feat",
      "subtype": ""
    },
    "requirements": "",
    "recharge": {
      "value": null,
      "charged": false
    }
  },
  "flags": {},
  "img": "",
  "effects": [],
  "folder": null,
  "sort": 0,
  "_stats": {
    "systemId": "dnd5e",
    "systemVersion": "2.1.0",
    "coreVersion": "10.291",
    "createdTime": 1676257596879,
    "modifiedTime": 1676257596879,
    "lastModifiedBy": "RightHandOfVecna"
  }
}
