{
  "_id": "X08LCrbqpHLpeYDu",
  "name": "Feat: Dragon Hide",
  "ownership": {
    "default": 0
  },
  "type": "feat",
  "system": {
    "description": {
      "value": "<p>You manifest scales and claws reminiscent of your draconic ancestors. You gain the following benefits:</p>\n<ul>\n<li>Increase your Strength, Constitution, or Charisma score by 1, up to a maximum of 20.</li>\n<li>Your scales harden. While you aren't wearing armor, you can calculate your AC as 13 + your Dexterity modifier. You can use a shield and still gain this benefit.</li>\n<li>You can grow retractable claws from the tips of your fingers. Extending or retracting the claws requires no action. The claws are natural weapons, which you can use to make unarmed strikes. If you hit with them, you deal slashing damage equal to 1d4 + your Strength modifier, instead of the normal bludgeoning damage for an unarmed strike.</li>\n</ul>",
      "chat": "",
      "unidentified": ""
    },
    "source": "SRD 5.1",
    "activation": {
      "type": "",
      "cost": null,
      "condition": ""
    },
    "duration": {
      "value": "",
      "units": ""
    },
    "cover": null,
    "target": {
      "value": null,
      "width": null,
      "units": "",
      "type": ""
    },
    "range": {
      "value": null,
      "long": null,
      "units": ""
    },
    "uses": {
      "value": null,
      "max": "",
      "per": null,
      "recovery": ""
    },
    "consume": {
      "type": "",
      "target": null,
      "amount": null
    },
    "ability": null,
    "actionType": "",
    "attackBonus": "",
    "chatFlavor": "",
    "critical": {
      "threshold": null,
      "damage": ""
    },
    "damage": {
      "parts": [],
      "versatile": ""
    },
    "formula": "",
    "save": {
      "ability": "",
      "dc": null,
      "scaling": "spell"
    },
    "type": {
      "value": "feat",
      "subtype": ""
    },
    "requirements": "Dragonborn",
    "recharge": {
      "value": null,
      "charged": false
    }
  },
  "flags": {},
  "img": "",
  "effects": [],
  "folder": null,
  "sort": 0,
  "_stats": {
    "systemId": "dnd5e",
    "systemVersion": "2.1.0",
    "coreVersion": "10.291",
    "createdTime": 1676257596723,
    "modifiedTime": 1676257596723,
    "lastModifiedBy": "RightHandOfVecna"
  }
}
