{
  "_id": "zElYrOcCFFMhB6Xl",
  "name": "Metamagic: Careful Spell",
  "ownership": {
    "default": 0
  },
  "type": "feat",
  "system": {
    "description": {
      "value": "<p>When you cast a spell that forces other creatures to make a saving throw, you can protect some of those creatures from the spell's full force. To do so, you spend 1 sorcery point and choose a number of those creatures up to your Charisma modifier (minimum of one creature). A chosen creature automatically succeeds on its saving throw against the spell.</p>",
      "chat": "",
      "unidentified": ""
    },
    "source": {
      "custom": "",
      "book": "SRD 5.1",
      "page": "",
      "license": "CC-BY-4.0"
    },
    "activation": {
      "type": "special",
      "cost": null,
      "condition": ""
    },
    "duration": {
      "value": "",
      "units": ""
    },
    "cover": null,
    "target": {
      "value": null,
      "width": null,
      "units": "",
      "type": ""
    },
    "range": {
      "value": null,
      "long": null,
      "units": ""
    },
    "uses": {
      "value": null,
      "max": "",
      "per": null,
      "recovery": ""
    },
    "consume": {
      "type": "",
      "target": null,
      "amount": null
    },
    "ability": "",
    "actionType": "",
    "attackBonus": "",
    "chatFlavor": "",
    "critical": {
      "threshold": null,
      "damage": ""
    },
    "damage": {
      "parts": [],
      "versatile": ""
    },
    "formula": "",
    "save": {
      "ability": "",
      "dc": null,
      "scaling": "spell"
    },
    "type": {
      "value": "class",
      "subtype": "metamagic"
    },
    "requirements": "Sorcerer 3",
    "recharge": {
      "value": null,
      "charged": false
    }
  },
  "flags": {},
  "img": "icons/magic/nature/beam-hand-leaves-green.webp",
  "effects": [],
  "folder": null,
  "sort": 0,
  "_stats": {
    "systemId": "dnd5e",
    "systemVersion": "2.1.0",
    "coreVersion": "10.291",
    "createdTime": 1661787234445,
    "modifiedTime": 1672334973777,
    "lastModifiedBy": "dnd5ebuilder0000"
  },
  "_key": "!items!zElYrOcCFFMhB6Xl"
}
