{
  "_id": "HUOPQ90Y9RXQHWOW",
  "name": "Psionic Power: Homing Strikes",
  "ownership": {
    "default": 0
  },
  "type": "feat",
  "system": {
    "description": {
      "value": "<p>If you make an attack roll with your Psychic Blades and miss the target, you can roll one Psionic Energy die and add the number rolled to the attack roll. If this causes the attack to hit, you expend the Psionic Energy die.</p>",
      "chat": "",
      "unidentified": ""
    },
    "source": "SRD 5.1",
    "activation": {
      "type": "",
      "cost": null,
      "condition": ""
    },
    "duration": {
      "value": "",
      "units": ""
    },
    "cover": null,
    "target": {
      "value": null,
      "width": null,
      "units": "",
      "type": ""
    },
    "range": {
      "value": null,
      "long": null,
      "units": ""
    },
    "uses": {
      "value": null,
      "max": "",
      "per": null,
      "recovery": ""
    },
    "consume": {
      "type": "",
      "target": null,
      "amount": null
    },
    "ability": null,
    "actionType": "",
    "attackBonus": "",
    "chatFlavor": "",
    "critical": {
      "threshold": null,
      "damage": ""
    },
    "damage": {
      "parts": [],
      "versatile": ""
    },
    "formula": "",
    "save": {
      "ability": "",
      "dc": null,
      "scaling": "spell"
    },
    "type": {
      "value": "class",
      "subtype": "psionicPower"
    },
    "requirements": "Soulknife 9",
    "recharge": {
      "value": null,
      "charged": false
    }
  },
  "flags": {},
  "img": "",
  "effects": [],
  "folder": null,
  "sort": 0,
  "_stats": {
    "systemId": "dnd5e",
    "systemVersion": "2.1.0",
    "coreVersion": "10.291",
    "createdTime": 1675986804092,
    "modifiedTime": 1675986804092,
    "lastModifiedBy": "dnd5ebuilder0000"
  }
}
