{
  "_id": "JMIQ09NECYEF5XQC",
  "name": "Immovable Object",
  "ownership": {
    "default": 0
  },
  "type": "spell",
  "system": {
    "description": {
      "value": "<p>You touch an object that weighs no more than 10 pounds and cause it to become magically fixed in place. You and the creatures you designate when you cast this spell can move the object normally. You can also set a password that, when spoken within 5 feet of the object, suppresses this spell for 1 minute.</p><p>If the object is fixed in the air, it can hold up to 4,000 pounds of weight. More weight causes the object to fall. Otherwise, a creature can use an action to make a Strength check against your spell save DC. On a success, the creature can move the object up to 10 feet.</p><p><strong><em>At Higher Levels:</em></strong> If you cast this spell using a spell slot of 5th or 6th level, the DC to move the object increases by 5, it can carry up to 8,000 pounds of weight, and the duration increases to 24 hours.</p>",
      "chat": "",
      "unidentified": ""
    },
    "source": "SRD 5.1",
    "activation": {
      "type": "action",
      "cost": 1,
      "condition": ""
    },
    "duration": {
      "value": "1",
      "units": "hour"
    },
    "cover": null,
    "target": {
      "value": 1,
      "width": null,
      "units": "",
      "type": "creature"
    },
    "range": {
      "value": null,
      "long": null,
      "units": "touch"
    },
    "uses": {
      "value": null,
      "max": "",
      "per": null,
      "recovery": ""
    },
    "consume": {
      "type": "",
      "target": null,
      "amount": null
    },
    "ability": "",
    "actionType": "util",
    "attackBonus": "",
    "chatFlavor": "",
    "critical": {
      "threshold": null,
      "damage": ""
    },
    "damage": {
      "parts": [],
      "versatile": ""
    },
    "formula": "",
    "save": {
      "ability": "",
      "dc": null,
      "scaling": "spell"
    },
    "level": 3,
    "school": "trs",
    "components": {
      "vocal": true,
      "somatic": true,
      "material": true,
      "ritual": false,
      "concentration": false
    },
    "materials": {
      "value": "Gold dust worth at least 25 gp, which the spell consumes",
      "consumed": true,
      "cost": 25,
      "supply": 0
    },
    "preparation": {
      "mode": "prepared",
      "prepared": false
    },
    "scaling": {
      "mode": "level",
      "formula": ""
    }
  },
  "sort": 0,
  "flags": {},
  "img": "icons/magic/water/pseudopod-swirl-blue.webp",
  "effects": [],
  "folder": null,
  "_stats": {
    "systemId": "dnd5e",
    "systemVersion": "2.1.0",
    "coreVersion": "10.291",
    "createdTime": 1675986797844,
    "modifiedTime": 1675989934444,
    "lastModifiedBy": "RightHandOfVecna"
  }
}
