{
  "_id": "vrN18tbTw7io5MWd",
  "name": "Chill Touch",
  "ownership": {
    "default": 0
  },
  "type": "spell",
  "system": {
    "description": {
      "value": "<p>You create a ghostly, skeletal hand in the space of a creature within range. Make a ranged spell attack against the creature to assail it with the chill of the grave. On a hit, the target takes 1d8 Necrotic damage, and it can't regain hit points until the start of your next turn. Until then, the hand clings to the target.</p><p>If you hit an undead target, it also has disadvantage on attack rolls against you until the end of your next turn.</p><p>This spell's damage increases by 1d8 when you reach 5th level (2d8), 11th level (3d8), and 17th level (4d8).</p>",
      "chat": "",
      "unidentified": ""
    },
    "source": "SRD 5.1",
    "activation": {
      "type": "action",
      "cost": 1,
      "condition": ""
    },
    "duration": {
      "value": "1",
      "units": "round"
    },
    "cover": null,
    "target": {
      "value": 1,
      "width": null,
      "units": "",
      "type": "creature"
    },
    "range": {
      "value": 120,
      "long": null,
      "units": "ft"
    },
    "uses": {
      "value": null,
      "max": "",
      "per": null,
      "recovery": ""
    },
    "consume": {
      "type": "",
      "target": null,
      "amount": null
    },
    "ability": "",
    "actionType": "rsak",
    "attackBonus": "",
    "chatFlavor": "",
    "critical": {
      "threshold": null,
      "damage": ""
    },
    "damage": {
      "parts": [
        [
          "1d8",
          "necrotic"
        ]
      ],
      "versatile": ""
    },
    "formula": "",
    "save": {
      "ability": "",
      "dc": null,
      "scaling": "spell"
    },
    "level": 0,
    "school": "nec",
    "components": {
      "vocal": true,
      "somatic": true,
      "material": false,
      "ritual": false,
      "concentration": false
    },
    "materials": {
      "value": "",
      "consumed": false,
      "cost": 0,
      "supply": 0
    },
    "preparation": {
      "mode": "prepared",
      "prepared": false
    },
    "scaling": {
      "mode": "cantrip",
      "formula": ""
    }
  },
  "sort": 0,
  "flags": {},
  "img": "icons/magic/water/projectile-ice-faceted-blue.webp",
  "effects": [],
  "folder": null,
  "_stats": {
    "systemId": "dnd5e",
    "systemVersion": "2.1.0",
    "coreVersion": "10.291",
    "createdTime": 1661787234237,
    "modifiedTime": 1671220971381,
    "lastModifiedBy": "dnd5ebuilder0000"
  },
  "_key": "!items!vrN18tbTw7io5MWd"
}
