{
  "_id": "ORowtOEh9kwfYWPo",
  "name": "Ancestry: Tabaxi",
  "ownership": {
    "default": 0
  },
  "type": "feat",
  "system": {
    "description": {
      "value": "<p>Your tabaxi character has the following ancestral traits.</p>\n<p><strong><em>Age.</em></strong> Tabaxi have lifespans equivalent to humans.</p>\n<p><strong><em>Size.</em></strong> Tabaxi are taller on average than humans and relatively slender. Your size is Medium.</p>\n<p><strong><em>Speed.</em></strong> Your base walking speed is 30 feet.</p>\n<p><strong><em>Feline Agility.</em></strong> @UUID[Compendium.dnd5e.races.un30XhgDUt9hGsIt]{Feline Agility} Your reflexes and agility allow you to move with a burst of speed. When you move on your turn in combat, you can move an additional 30 feet. Once you use this trait, you can't use it again until you move 0 feet on one of your turns.</p>\n<p><strong><em>Cat's Claws.</em></strong> @UUID[Compendium.dnd5e.races.pyTnLPS1NMQnkwxM]{Cat's Claws} Because of your claws, you have a climbing speed of 20 feet. In addition, your claws are natural weapons, which you can use to make unarmed strikes. If you hit with them, you deal slashing damage equal to 1d4 + your Strength modifier, instead of the bludgeoning damage normal for an unarmed strike.</p>\n<p><strong><em>Cat's Talent.</em></strong> You have proficiency in the Perception and Stealth skills.</p>\n<section class=\"secret foundry-note\">\n<p><strong>Foundry Note</strong></p>\n<p>You can drag your choices from the above onto your character sheet and it will automatically update.</p>\n</section>",
      "chat": "",
      "unidentified": ""
    },
    "source": "SRD 5.1",
    "activation": {
      "type": "",
      "cost": null,
      "condition": ""
    },
    "duration": {
      "value": "",
      "units": ""
    },
    "cover": null,
    "target": {
      "value": null,
      "width": null,
      "units": "",
      "type": ""
    },
    "range": {
      "value": null,
      "long": null,
      "units": ""
    },
    "uses": {
      "value": null,
      "max": "",
      "per": null,
      "recovery": ""
    },
    "consume": {
      "type": "",
      "target": null,
      "amount": null
    },
    "ability": null,
    "actionType": "",
    "attackBonus": "",
    "chatFlavor": "",
    "critical": {
      "threshold": null,
      "damage": ""
    },
    "damage": {
      "parts": [],
      "versatile": ""
    },
    "formula": "",
    "save": {
      "ability": "",
      "dc": null,
      "scaling": "spell"
    },
    "type": {
      "value": "class",
      "subtype": ""
    },
    "requirements": "",
    "recharge": {
      "value": null,
      "charged": false
    }
  },
  "flags": {},
  "img": "icons/creatures/mammals/cat-hunched-glowing-red.webp",
  "effects": [
    {
      "_id": "9JkHeDUbAxkErFl8",
      "changes": [
        {
          "key": "system.skills.per.value",
          "mode": 5,
          "value": "1",
          "priority": null
        },
        {
          "key": "system.skills.ste.value",
          "mode": 5,
          "value": "1",
          "priority": null
        }
      ],
      "disabled": false,
      "duration": {
        "startTime": null,
        "seconds": null,
        "combat": null,
        "rounds": null,
        "turns": null,
        "startRound": null,
        "startTurn": null
      },
      "icon": "icons/creatures/mammals/cat-hunched-glowing-red.webp",
      "label": "Tabaxi Ancestry",
      "origin": "Item.ORowtOEh9kwfYWPo",
      "transfer": true,
      "flags": {},
      "tint": null,
      "sort": 0
    }
  ],
  "folder": null,
  "sort": 0,
  "_stats": {
    "systemId": "dnd5e",
    "systemVersion": "2.1.0",
    "coreVersion": "10.291",
    "createdTime": 1676598659930,
    "modifiedTime": 1676598659930,
    "lastModifiedBy": "RightHandOfVecna"
  }
}
