{
  "_id": "yD51x4dihnbHwfsj",
  "name": "Trampling Charge",
  "ownership": {
    "default": 0
  },
  "type": "feat",
  "system": {
    "description": {
      "value": "<section class=\"secret\">\n<p>If the {creature} moves at least <strong>20 ft.</strong> straight toward a creature and then hits it with a gore attack on the same turn, that target must succeed on a <strong>DC 12 Strength saving throw</strong> or be knocked prone. If the target is prone, the {creature} can make one stomp attack against it as a bonus action.</p>\n</section>\n<p>If the {creature} moves at least <strong>20 ft.</strong> straight toward a creature and then hits it with a gore attack on the same turn, that target must succeed on a Strength saving throw.</p>",
      "chat": "",
      "unidentified": ""
    },
    "source": "",
    "activation": {
      "type": "",
      "cost": null,
      "condition": ""
    },
    "duration": {
      "value": null,
      "units": ""
    },
    "target": {
      "value": null,
      "width": null,
      "units": "",
      "type": ""
    },
    "range": {
      "value": 20,
      "long": null,
      "units": "ft"
    },
    "uses": {
      "value": 0,
      "max": 0,
      "per": "",
      "type": ""
    },
    "consume": {
      "type": "",
      "target": "",
      "amount": null
    },
    "ability": "",
    "actionType": "other",
    "attackBonus": 0,
    "chatFlavor": "",
    "critical": {
      "threshold": null,
      "damage": ""
    },
    "damage": {
      "parts": [],
      "versatile": "",
      "value": ""
    },
    "formula": "",
    "save": {
      "ability": "str",
      "dc": 12,
      "scaling": "flat",
      "value": ""
    },
    "requirements": "",
    "recharge": {
      "value": null,
      "charged": false
    },
    "time": {
      "value": "",
      "_deprecated": true
    },
    "damageType": {
      "value": "",
      "_deprecated": true
    }
  },
  "flags": {},
  "img": "icons/creatures/abilities/cougar-pounce-stalk-black.webp",
  "effects": [],
  "folder": null,
  "sort": 0,
  "_stats": {
    "systemId": "dnd5e",
    "systemVersion": "2.0.0",
    "coreVersion": "10.279",
    "createdTime": 1661787234621,
    "modifiedTime": 1661787234621,
    "lastModifiedBy": "dnd5ebuilder0000"
  }
}
