{
  "_id": "9eOZDBImVKxbeOyZ",
  "name": "Enhance Ability",
  "ownership": {
    "default": 0
  },
  "type": "spell",
  "system": {
    "description": {
      "value": "<p>You touch a creature and bestow upon it a magical enhancement. Choose one of the following effects: the target gains the effect until the spell ends.</p><p><strong>Bear's Endurance:</strong> The target has advantage on Constitution checks. It also gains 2d6 temporary hit points, which are lost when the spell ends.</p><p><strong>Bull's Strength:</strong> The target has advantage on Strength checks, and his or her carrying capacity doubles.</p><p><strong>Cat's Grace:</strong> The target has advantage on Dexterity checks. It also doesn't take damage from falling 20 feet or less if it isn't incapacitated.</p><p><strong>Eagle's Splendor:</strong> The target has advantage on Charisma checks.</p><p><strong>Fox's Cunning:</strong> The target has advantage on Intelligence checks.</p><p><strong>Owl's Wisdom:</strong> The target has advantage on Wisdom checks.</p><p><strong><em>At Higher Levels:</em></strong> When you cast this spell using a spell slot of 3rd level or higher, you can target one additional creature for each slot level above 2nd.</p>",
      "chat": "",
      "unidentified": ""
    },
    "source": "SRD 5.1",
    "activation": {
      "type": "action",
      "cost": 1,
      "condition": ""
    },
    "duration": {
      "value": "1",
      "units": "hour"
    },
    "cover": null,
    "target": {
      "value": 1,
      "width": null,
      "units": "",
      "type": "creature"
    },
    "range": {
      "value": null,
      "long": null,
      "units": "touch"
    },
    "uses": {
      "value": null,
      "max": "",
      "per": null,
      "recovery": ""
    },
    "consume": {
      "type": "",
      "target": null,
      "amount": null
    },
    "ability": "",
    "actionType": "util",
    "attackBonus": "",
    "chatFlavor": "",
    "critical": {
      "threshold": null,
      "damage": ""
    },
    "damage": {
      "parts": [
        [
          "2d6",
          "temphp"
        ]
      ],
      "versatile": ""
    },
    "formula": "",
    "save": {
      "ability": "",
      "dc": null,
      "scaling": "spell"
    },
    "level": 2,
    "school": "trs",
    "components": {
      "vocal": true,
      "somatic": true,
      "material": true,
      "ritual": false,
      "concentration": true
    },
    "materials": {
      "value": "Fur or a feather from a beast",
      "consumed": false,
      "cost": 0,
      "supply": 0
    },
    "preparation": {
      "mode": "prepared",
      "prepared": false
    },
    "scaling": {
      "mode": "level",
      "formula": ""
    }
  },
  "sort": 0,
  "flags": {},
  "img": "icons/magic/control/buff-flight-wings-runes-purple.webp",
  "effects": [],
  "folder": null,
  "_stats": {
    "systemId": "dnd5e",
    "systemVersion": "2.1.0",
    "coreVersion": "10.291",
    "createdTime": 1661787234084,
    "modifiedTime": 1675989934172,
    "lastModifiedBy": "RightHandOfVecna"
  }
}
