{
  "_id": "8MICCMeOXT3aJUy9",
  "name": "Divine Favor",
  "ownership": {
    "default": 0
  },
  "type": "spell",
  "system": {
    "description": {
      "value": "<p>Your prayer empowers you with divine radiance. Until the spell ends, your weapon attacks deal an extra 1d4 radiant damage on a hit.</p>",
      "chat": "",
      "unidentified": ""
    },
    "source": "PHB pg. 234",
    "activation": {
      "type": "bonus",
      "cost": 1,
      "condition": ""
    },
    "duration": {
      "value": 1,
      "units": "minute"
    },
    "target": {
      "value": null,
      "width": null,
      "units": null,
      "type": "self"
    },
    "range": {
      "value": null,
      "long": null,
      "units": "self"
    },
    "uses": {
      "value": 0,
      "max": 0,
      "per": ""
    },
    "consume": {
      "type": "",
      "target": null,
      "amount": null
    },
    "ability": "",
    "actionType": "other",
    "attackBonus": 0,
    "chatFlavor": "",
    "critical": {
      "threshold": null,
      "damage": ""
    },
    "damage": {
      "parts": [
        [
          "1d4",
          "radiant"
        ]
      ],
      "versatile": "",
      "value": ""
    },
    "formula": "",
    "save": {
      "ability": "",
      "dc": null,
      "scaling": "spell",
      "value": ""
    },
    "level": 1,
    "school": "evo",
    "components": {
      "value": "",
      "vocal": true,
      "somatic": true,
      "material": false,
      "ritual": false,
      "concentration": true
    },
    "materials": {
      "value": "",
      "consumed": false,
      "cost": 0,
      "supply": 0
    },
    "preparation": {
      "mode": "prepared",
      "prepared": false
    },
    "scaling": {
      "mode": "none",
      "formula": ""
    }
  },
  "sort": 100001,
  "flags": {},
  "img": "icons/magic/fire/dagger-rune-enchant-flame-blue-yellow.webp",
  "effects": [],
  "folder": null,
  "_stats": {
    "systemId": "dnd5e",
    "systemVersion": "2.0.0",
    "coreVersion": "10.279",
    "createdTime": 1661787234079,
    "modifiedTime": 1661787234079,
    "lastModifiedBy": "dnd5ebuilder0000"
  }
}
