{
  "_id": "CKZTpZlxj7hjjo2H",
  "name": "Mage Armor",
  "type": "spell",
  "img": "icons/magic/defensive/shield-barrier-glowing-triangle-blue.webp",
  "system": {
    "description": {
      "value": "<p>You touch a willing creature who isn't wearing armor, and a protective magical force surrounds it until the spell ends. The target's base AC becomes 13 + its Dexterity modifier. The spell ends if the target dons armor or if you dismiss the spell as an action.</p>",
      "chat": "",
      "unidentified": ""
    },
    "source": "PHB pg. 256",
    "activation": {
      "type": "action",
      "cost": 1,
      "condition": ""
    },
    "duration": {
      "value": 8,
      "units": "hour"
    },
    "target": {
      "value": 1,
      "width": null,
      "units": "",
      "type": "creature"
    },
    "range": {
      "value": null,
      "long": null,
      "units": "touch"
    },
    "uses": {
      "value": 0,
      "max": 0,
      "per": ""
    },
    "consume": {
      "type": "",
      "target": null,
      "amount": null
    },
    "ability": "",
    "actionType": "util",
    "attackBonus": 0,
    "chatFlavor": "",
    "critical": {
      "threshold": null,
      "damage": ""
    },
    "damage": {
      "parts": [],
      "versatile": "",
      "value": ""
    },
    "formula": "",
    "save": {
      "ability": "",
      "dc": null,
      "scaling": "spell",
      "value": ""
    },
    "level": 1,
    "school": "abj",
    "components": {
      "value": "",
      "vocal": true,
      "somatic": true,
      "material": true,
      "ritual": false,
      "concentration": false
    },
    "materials": {
      "value": "A piece of cured leather",
      "consumed": false,
      "cost": 0,
      "supply": 0
    },
    "preparation": {
      "mode": "prepared",
      "prepared": false
    },
    "scaling": {
      "mode": "none",
      "formula": ""
    }
  },
  "effects": [
    {
      "_id": "cfwMU7LuOJ619Lny",
      "changes": [
        {
          "key": "system.attributes.ac.calc",
          "value": "mage",
          "mode": 5,
          "priority": null
        }
      ],
      "disabled": true,
      "duration": {
        "startTime": null,
        "seconds": null,
        "combat": null,
        "rounds": null,
        "turns": null,
        "startRound": null,
        "startTurn": null
      },
      "icon": "icons/magic/defensive/shield-barrier-glowing-triangle-blue.webp",
      "label": "Mage Armor",
      "origin": "Compendium.dnd5e.spells.CKZTpZlxj7hjjo2H",
      "transfer": true,
      "flags": {},
      "tint": null
    }
  ],
  "folder": null,
  "sort": 100001,
  "ownership": {
    "default": 0
  },
  "flags": {},
  "_stats": {
    "systemId": "dnd5e",
    "systemVersion": "2.0.0",
    "coreVersion": "10.279",
    "createdTime": 1661787234095,
    "modifiedTime": 1661787234095,
    "lastModifiedBy": "dnd5ebuilder0000"
  }
}
