{
  "_id": "UrH3sMdnUDckIHJ6",
  "name": "Flail",
  "type": "weapon",
  "img": "icons/weapons/maces/mace-round-spiked-black.webp",
  "system": {
    "description": {
      "value": "<p>A set of chain-linked spiked balls lashed to a stout wooden shaft. The flail deals devastating damage when whirled in a deadly arc.</p>",
      "chat": "",
      "unidentified": ""
    },
    "source": "SRD 5.1",
    "quantity": 1,
    "weight": 2,
    "price": {
      "value": 10,
      "denomination": "gp"
    },
    "attunement": 0,
    "equipped": false,
    "rarity": "",
    "identified": true,
    "activation": {
      "type": "action",
      "cost": 1,
      "condition": ""
    },
    "duration": {
      "value": "",
      "units": ""
    },
    "cover": null,
    "target": {
      "value": null,
      "width": null,
      "units": "",
      "type": ""
    },
    "range": {
      "value": 5,
      "long": null,
      "units": "ft"
    },
    "uses": {
      "value": null,
      "max": "",
      "per": null,
      "recovery": ""
    },
    "consume": {
      "type": "",
      "target": null,
      "amount": null
    },
    "ability": null,
    "actionType": "mwak",
    "attackBonus": "",
    "chatFlavor": "",
    "critical": {
      "threshold": null,
      "damage": ""
    },
    "damage": {
      "parts": [
        [
          "1d8+@mod",
          "bludgeoning"
        ]
      ],
      "versatile": ""
    },
    "formula": "",
    "save": {
      "ability": "",
      "dc": null,
      "scaling": "spell"
    },
    "armor": {
      "value": 10
    },
    "hp": {
      "value": 0,
      "max": 0,
      "dt": null,
      "conditions": ""
    },
    "weaponType": "martialM",
    "baseItem": "flail",
    "properties": {
      "amm": false,
      "hvy": false,
      "fin": false,
      "fir": false,
      "foc": false,
      "lgt": false,
      "rch": false,
      "rel": false,
      "ret": false,
      "spc": false,
      "thr": false,
      "two": false,
      "ver": false
    },
    "proficient": null
  },
  "effects": [],
  "folder": null,
  "sort": 0,
  "ownership": {
    "default": 0
  },
  "flags": {},
  "_stats": {
    "systemId": "dnd5e",
    "systemVersion": "2.1.0",
    "coreVersion": "10.291",
    "createdTime": 1661787233680,
    "modifiedTime": 1671220961264,
    "lastModifiedBy": "dnd5ebuilder0000"
  },
  "_key": "!items!UrH3sMdnUDckIHJ6"
}
