{
  "_id": "DWLMnODrnHn8IbAG",
  "name": "Javelin",
  "type": "weapon",
  "img": "icons/weapons/ammunition/arrows-bodkin-yellow-red.webp",
  "system": {
    "description": {
      "value": "<p>This light and flexible spear is designed for throwing, but is versatile enough to be used in melee combat as well.</p>",
      "chat": "",
      "unidentified": ""
    },
    "source": "SRD 5.1",
    "quantity": 1,
    "weight": 2,
    "price": {
      "value": 5,
      "denomination": "sp"
    },
    "attunement": 0,
    "equipped": false,
    "rarity": "common",
    "identified": true,
    "activation": {
      "type": "action",
      "cost": 1,
      "condition": ""
    },
    "duration": {
      "value": "",
      "units": ""
    },
    "cover": null,
    "target": {
      "value": null,
      "width": null,
      "units": "",
      "type": ""
    },
    "range": {
      "value": 30,
      "long": 120,
      "units": "ft"
    },
    "uses": {
      "value": null,
      "max": "",
      "per": null,
      "recovery": ""
    },
    "consume": {
      "type": "",
      "target": null,
      "amount": null
    },
    "ability": null,
    "actionType": "mwak",
    "attackBonus": "",
    "chatFlavor": "",
    "critical": {
      "threshold": null,
      "damage": ""
    },
    "damage": {
      "parts": [
        [
          "1d6 + @mod",
          "piercing"
        ]
      ],
      "versatile": ""
    },
    "formula": "",
    "save": {
      "ability": "",
      "dc": null,
      "scaling": "spell"
    },
    "armor": {
      "value": 10
    },
    "hp": {
      "value": 0,
      "max": 0,
      "dt": null,
      "conditions": ""
    },
    "type": { "value": "simpleM", "subtype": "", "baseItem": "" },
    "baseItem": "javelin",
    "properties": {
      "thr": true,
      "amm": false,
      "hvy": false,
      "fin": false,
      "fir": false,
      "foc": false,
      "lgt": false,
      "rch": false,
      "rel": false,
      "ret": false,
      "spc": false,
      "two": false,
      "ver": false,
      "lod": false
    },
    "proficient": false
  },
  "effects": [],
  "folder": null,
  "sort": 0,
  "ownership": {
    "default": 0
  },
  "flags": {},
  "_stats": {
    "systemId": "dnd5e",
    "systemVersion": "2.1.0",
    "coreVersion": "10.291",
    "createdTime": 1661787233527,
    "modifiedTime": 1671220958767,
    "lastModifiedBy": "dnd5ebuilder0000"
  }
}
