{
  "_id": "GsuvwoekKZatfKwF",
  "name": "Unarmed Strike",
  "type": "weapon",
  "img": "icons/skills/melee/unarmed-punch-fist-yellow-red.webp",
  "system": {
    "description": {
      "value": "<p>A  punch, kick, head-butt, or similar forceful blow (none of which count as weapons). On a hit, an unarmed strike deals bludgeoning damage equal to 1 + your Strength modifier. You are proficient with your unarmed strikes.</p>",
      "chat": "",
      "unidentified": ""
    },
    "source": "SRD 5.1",
    "quantity": 1,
    "weight": 0,
    "price": {
      "value": 0,
      "denomination": "gp"
    },
    "attunement": 0,
    "equipped": false,
    "rarity": "",
    "identified": true,
    "activation": {
      "type": "action",
      "cost": 1,
      "condition": ""
    },
    "duration": {
      "value": "",
      "units": ""
    },
    "cover": null,
    "target": {
      "value": null,
      "width": null,
      "units": "",
      "type": ""
    },
    "range": {
      "value": 5,
      "long": null,
      "units": "ft"
    },
    "uses": {
      "value": null,
      "max": "",
      "per": null,
      "recovery": ""
    },
    "consume": {
      "type": "",
      "target": null,
      "amount": null
    },
    "ability": "str",
    "actionType": "mwak",
    "attackBonus": "",
    "chatFlavor": "",
    "critical": {
      "threshold": null,
      "damage": ""
    },
    "damage": {
      "parts": [
        [
          "1 + @mod",
          "bludgeoning"
        ]
      ],
      "versatile": ""
    },
    "formula": "",
    "save": {
      "ability": "",
      "dc": null,
      "scaling": "spell"
    },
    "armor": {
      "value": 10
    },
    "hp": {
      "value": 0,
      "max": 0,
      "dt": null,
      "conditions": ""
    },
    "weaponType": "simpleM",
    "baseItem": "",
    "properties": {
      "amm": false,
      "hvy": false,
      "fin": false,
      "fir": false,
      "foc": false,
      "lgt": false,
      "lod": false,
      "rch": false,
      "rel": false,
      "ret": false,
      "spc": false,
      "thr": false,
      "two": false,
      "ver": false,
      "mgc": false
    },
    "proficient": true
  },
  "effects": [],
  "folder": null,
  "sort": 0,
  "ownership": {
    "default": 0
  },
  "flags": {},
  "_stats": {
    "systemId": "dnd5e",
    "systemVersion": "2.1.0",
    "coreVersion": "10.291",
    "createdTime": 1661787233557,
    "modifiedTime": 1671220959127,
    "lastModifiedBy": "dnd5ebuilder0000"
  }
}
